cases/__init__.py
cases/admin.py
cases/apps.py
cases/models.py
cases/tests.py
cases/urls.py
cases/views.py
cases/migrations/0001_initial.py
cases/migrations/__init__.py
cases/static/cases/css/style.css
cases/static/cases/js/case_slider.js
cases/static/cases/js/main.js
cases/static/cases/vendor/animate.css/animate.compat.css
cases/static/cases/vendor/animate.css/animate.css
cases/static/cases/vendor/animate.css/animate.min.css
cases/static/cases/vendor/bootstrap/css/bootstrap-grid.css
cases/static/cases/vendor/bootstrap/css/bootstrap-grid.css.map
cases/static/cases/vendor/bootstrap/css/bootstrap-grid.min.css
cases/static/cases/vendor/bootstrap/css/bootstrap-grid.min.css.map
cases/static/cases/vendor/bootstrap/css/bootstrap-grid.rtl.css
cases/static/cases/vendor/bootstrap/css/bootstrap-grid.rtl.css.map
cases/static/cases/vendor/bootstrap/css/bootstrap-grid.rtl.min.css
cases/static/cases/vendor/bootstrap/css/bootstrap-grid.rtl.min.css.map
cases/static/cases/vendor/bootstrap/css/bootstrap-reboot.css
cases/static/cases/vendor/bootstrap/css/bootstrap-reboot.css.map
cases/static/cases/vendor/bootstrap/css/bootstrap-reboot.min.css
cases/static/cases/vendor/bootstrap/css/bootstrap-reboot.min.css.map
cases/static/cases/vendor/bootstrap/css/bootstrap-reboot.rtl.css
cases/static/cases/vendor/bootstrap/css/bootstrap-reboot.rtl.css.map
cases/static/cases/vendor/bootstrap/css/bootstrap-reboot.rtl.min.css
cases/static/cases/vendor/bootstrap/css/bootstrap-reboot.rtl.min.css.map
cases/static/cases/vendor/bootstrap/css/bootstrap-utilities.css
cases/static/cases/vendor/bootstrap/css/bootstrap-utilities.css.map
cases/static/cases/vendor/bootstrap/css/bootstrap-utilities.min.css
cases/static/cases/vendor/bootstrap/css/bootstrap-utilities.min.css.map
cases/static/cases/vendor/bootstrap/css/bootstrap-utilities.rtl.css
cases/static/cases/vendor/bootstrap/css/bootstrap-utilities.rtl.css.map
cases/static/cases/vendor/bootstrap/css/bootstrap-utilities.rtl.min.css
django_cases-0.0.4.dist-info/LICENSE
django_cases-0.0.4.dist-info/METADATA
django_cases-0.0.4.dist-info/WHEEL
django_cases-0.0.4.dist-info/top_level.txt
django_cases-0.0.4.dist-info/RECORD
